stat_analys/__init__.py
stat_analys/configuration.py
stat_analys/univariate_stat.py
stat_analys/utils.py
stat_analys/visualizations.py
test/__init__.py
test/test_configuration.py
stat_analys-0.1.1.dist-info/METADATA
stat_analys-0.1.1.dist-info/WHEEL
stat_analys-0.1.1.dist-info/top_level.txt
stat_analys-0.1.1.dist-info/RECORD
