Metadata-Version: 2.1
Name: stat_analys
Version: 0.1.1
Summary: Un package pour l'analyse statistique univariee
Home-page: https://github.com/Jean-Paul15/stat_analys
Author: ADOGLI Jean-Paul
Author-email: adoglijeanpaul@gmail.com
Classifier: Programming Language :: Python :: 3
Classifier: License :: OSI Approved :: MIT License
Classifier: Operating System :: OS Independent
Requires-Python: >=3.7
Requires-Dist: pandas
Requires-Dist: numpy
Requires-Dist: seaborn
Requires-Dist: matplotlib
Requires-Dist: plotly
Requires-Dist: scipy
Requires-Dist: scikit-learn
Requires-Dist: tabulate
